pygments_gemini.py
pygments_gemini-0.1.0.dist-info/entry_points.txt
pygments_gemini-0.1.0.dist-info/LICENSE
pygments_gemini-0.1.0.dist-info/WHEEL
pygments_gemini-0.1.0.dist-info/METADATA
pygments_gemini-0.1.0.dist-info/RECORD
