Metadata-Version: 2.1
Name: pygments-gemini
Version: 0.1.0
Summary: Gemini Lexer for Pygments
License: BSD
Author: Kyle Fuller
Author-email: kyle@fuller.li
Requires-Python: >=3.6,<4.0
Classifier: License :: Other/Proprietary License
Classifier: Programming Language :: Python :: 3
Classifier: Programming Language :: Python :: 3.6
Classifier: Programming Language :: Python :: 3.7
Classifier: Programming Language :: Python :: 3.8
Classifier: Programming Language :: Python :: 3.9
Requires-Dist: Pygments (>=2.9.0,<3.0.0)
